sri_checker.py
sri_checker-0.1.1.dist-info/LICENCE
sri_checker-0.1.1.dist-info/METADATA
sri_checker-0.1.1.dist-info/WHEEL
sri_checker-0.1.1.dist-info/entry_points.txt
sri_checker-0.1.1.dist-info/top_level.txt
sri_checker-0.1.1.dist-info/RECORD
