Metadata-Version: 2.1
Name: sri-checker
Version: 0.1.1
Summary: a linter and pre-commit hook to check SRI-hashes in HTML files
Home-page: https://github.com/jkittner/sri-checker
Author: Jonas Kittner
Author-email: jkittner@users.noreply.github.com
License: MIT
Classifier: License :: OSI Approved :: MIT License
Classifier: Programming Language :: Python :: 3
Classifier: Programming Language :: Python :: 3 :: Only
Classifier: Programming Language :: Python :: Implementation :: CPython
Requires-Python: >=3.9
License-File: LICENCE
Requires-Dist: beautifulsoup4
